aiodatacube/__init__.py
aiodatacube/datacubeclient.py
aiodatacube/stub/__init__.py
aiodatacube/stub/datacube_p2p.py
aiodatacube/stub/datacube_pb2.py
aiodatacube/stub/datacube_pb2_grpc.py
aiodatacube-0.1.5.dist-info/licenses/LICENSE
aiodatacube-0.1.5.dist-info/METADATA
aiodatacube-0.1.5.dist-info/WHEEL
aiodatacube-0.1.5.dist-info/top_level.txt
aiodatacube-0.1.5.dist-info/RECORD
