Metadata-Version: 2.4
Name: aiodatacube
Version: 0.1.5
Author-email: Abul Basar <dev@avalanchio.com>
License-Expression: MIT
Keywords: datacube,avalanchio
Requires-Python: >=3.8
License-File: LICENSE
Requires-Dist: pydantic
Requires-Dist: grpcio
Dynamic: license-file
